<?xml version="1.0" encoding="utf-8" ?><dwsync><file name="เฉลยPAT1-2554-30-01.png" server="ftp.zodsai.com/public_html/" local="3387584610" remote="318763443816808152" Dst="-1" /><file name="เฉลยPAT1-2554-30-03.png" server="ftp.zodsai.com/public_html/" local="3387584612" remote="318763443816808152" Dst="-1" /><file name="เฉลยPAT1-2554-30-02.png" server="ftp.zodsai.com/public_html/" local="3387584610" remote="318763443816808152" Dst="-1" /><file name="เฉลยPAT1-2554-30-05.png" server="ftp.zodsai.com/public_html/" local="3387584614" remote="318763443816808152" Dst="-1" /><file name="เฉลยPAT1-2554-30-04.png" server="ftp.zodsai.com/public_html/" local="3387584614" remote="318763443816808152" Dst="-1" /><file name="เฉลยPAT1-2554-30-07.png" server="ftp.zodsai.com/public_html/" local="3387584616" remote="318763443816808152" Dst="-1" /><file name="เฉลยPAT1-2554-30-06.png" server="ftp.zodsai.com/public_html/" local="3387584616" remote="318763443816808152" Dst="-1" /><file name="เฉลยPAT1-2554-30-08.png" server="ftp.zodsai.com/public_html/" local="3387584618" remote="318763443816808152" Dst="-1" /></dwsync>